goodbase/__init__.py
goodbase/build_checker.py
goodbase/clients/__init__.py
goodbase/clients/evg_cli_proxy.py
goodbase/goodbase_cli.py
goodbase/goodbase_options.py
goodbase/models/__init__.py
goodbase/models/build_status.py
goodbase/services/__init__.py
goodbase/services/config_service.py
goodbase/services/criteria_service.py
goodbase/services/evg_service.py
goodbase/services/file_service.py
goodbase/services/git_service.py
goodbase/services/search_service.py
git_co_evg_base-7.1.1.dist-info/METADATA
git_co_evg_base-7.1.1.dist-info/WHEEL
git_co_evg_base-7.1.1.dist-info/entry_points.txt
git_co_evg_base-7.1.1.dist-info/RECORD
