Metadata-Version: 2.3
Name: git-co-evg-base
Version: 7.1.1
Summary: Find a good commit to base your work on
Author: DevProd Services & Integrations Team
Author-email: devprod-si-team@mongodb.com
Requires-Python: >=3.9,<4.0
Classifier: Programming Language :: Python :: 3
Classifier: Programming Language :: Python :: 3.9
Classifier: Programming Language :: Python :: 3.10
Classifier: Programming Language :: Python :: 3.11
Classifier: Programming Language :: Python :: 3.12
Classifier: Programming Language :: Python :: 3.13
Requires-Dist: Inject (>=4.3.1,<5.0.0)
Requires-Dist: PyYAML (>=6.0.1,<7.0.0)
Requires-Dist: click (>=8,<9)
Requires-Dist: evergreen-py (>=3.6,<4.0)
Requires-Dist: plumbum (>=1.7.0,<2.0.0)
Requires-Dist: pydantic (>=1.8.2,<2.0.0)
Requires-Dist: rich (>=10.9.0,<11.0.0)
Requires-Dist: structlog (>=21.1.0,<22.0.0)
Requires-Dist: xdg (>=5.1.1,<6.0.0)
Project-URL: Repository, https://github.com/evergreen-ci/git-co-evg-base
